README.md
setup.py
wallet_one/__init__.py
wallet_one.egg-info/PKG-INFO
wallet_one.egg-info/SOURCES.txt
wallet_one.egg-info/dependency_links.txt
wallet_one.egg-info/not-zip-safe
wallet_one.egg-info/top_level.txt