Metadata-Version: 1.0
Name: wallet-one
Version: 0.11
Summary: Form wrapper for Wallet One Payments.
Home-page: http://github.com/everhide/wallet-one-payments
Author: everhide
Author-email: i.tolkachnikov@gmail.com
License: MIT
Platform: UNKNOWN
